belfrywidgets/__init__.py
belfrywidgets/collapsiblepane.py
belfrywidgets/labelbutton.py
belfrywidgets/progressbar.py
belfrywidgets/scrolledlistbox.py
belfrywidgets/tabbednotebook.py
belfrywidgets/tooltip.py
belfrywidgets/wizard.py
belfrywidgets-1.0.3.dist-info/DESCRIPTION.rst
belfrywidgets-1.0.3.dist-info/METADATA
belfrywidgets-1.0.3.dist-info/RECORD
belfrywidgets-1.0.3.dist-info/WHEEL
belfrywidgets-1.0.3.dist-info/metadata.json
belfrywidgets-1.0.3.dist-info/top_level.txt
