Metadata-Version: 2.0
Name: belfrywidgets
Version: 1.0.3
Summary: A collection of useful tkinter widgets.
Home-page: https://github.com/revarbat/belfrywidgets
Author: Revar Desmera
Author-email: revarbat@gmail.com
License: MIT License
Download-URL: https://github.com/revarbat/belfrywidgets/archive/master.zip
Keywords: tkinter widgets
Platform: UNKNOWN
Classifier: Development Status :: 4 - Beta
Classifier: Environment :: MacOS X
Classifier: Environment :: MacOS X :: Aqua
Classifier: Environment :: MacOS X :: Carbon
Classifier: Environment :: MacOS X :: Cocoa
Classifier: Intended Audience :: Developers
Classifier: License :: OSI Approved :: MIT License
Classifier: Operating System :: MacOS :: MacOS X
Classifier: Operating System :: Microsoft :: Windows
Classifier: Operating System :: POSIX
Classifier: Programming Language :: Python :: 2
Classifier: Programming Language :: Python :: 3
Classifier: Topic :: Software Development :: Libraries
Classifier: Topic :: Software Development :: Libraries :: Python Modules
Classifier: Topic :: Software Development :: Widget Sets
Requires-Dist: setuptools
